treevalue/__init__.py
treevalue/config/__init__.py
treevalue/config/meta.py
treevalue/entry/__init__.py
treevalue/entry/cli/__init__.py
treevalue/entry/cli/base.py
treevalue/entry/cli/dispatch.py
treevalue/entry/cli/export.py
treevalue/entry/cli/graph.py
treevalue/entry/cli/io.py
treevalue/entry/cli/utils.py
treevalue/entry/script/__init__.py
treevalue/tree/__init__.py
treevalue/tree/common/__init__.py
treevalue/tree/common/base.cp312-win_amd64.pyd
treevalue/tree/common/delay.cp312-win_amd64.pyd
treevalue/tree/common/storage.cp312-win_amd64.pyd
treevalue/tree/func/__init__.py
treevalue/tree/func/cfunc.cp312-win_amd64.pyd
treevalue/tree/func/func.py
treevalue/tree/func/modes.cp312-win_amd64.pyd
treevalue/tree/general/__init__.py
treevalue/tree/general/fast.py
treevalue/tree/general/general.py
treevalue/tree/integration/__init__.py
treevalue/tree/integration/base.cp312-win_amd64.pyd
treevalue/tree/integration/cjax.cp312-win_amd64.pyd
treevalue/tree/integration/ctorch.cp312-win_amd64.pyd
treevalue/tree/integration/general.cp312-win_amd64.pyd
treevalue/tree/integration/jax.py
treevalue/tree/integration/torch.py
treevalue/tree/tree/__init__.py
treevalue/tree/tree/constraint.cp312-win_amd64.pyd
treevalue/tree/tree/flatten.cp312-win_amd64.pyd
treevalue/tree/tree/functional.cp312-win_amd64.pyd
treevalue/tree/tree/graph.py
treevalue/tree/tree/io.py
treevalue/tree/tree/service.cp312-win_amd64.pyd
treevalue/tree/tree/structural.cp312-win_amd64.pyd
treevalue/tree/tree/tree.cp312-win_amd64.pyd
treevalue/utils/__init__.py
treevalue/utils/color.py
treevalue/utils/formattree.py
treevalue/utils/random.py
treevalue/utils/tree.py
treevalue-1.5.0.dist-info/LICENSE
treevalue-1.5.0.dist-info/METADATA
treevalue-1.5.0.dist-info/WHEEL
treevalue-1.5.0.dist-info/entry_points.txt
treevalue-1.5.0.dist-info/top_level.txt
treevalue-1.5.0.dist-info/RECORD
