Metadata-Version: 2.1
Name: treevalue
Version: 1.5.0
Summary: A flexible, generalized tree-based data structure.
Home-page: https://github.com/HansBug/treevalue
Author: HansBug, DI-engine's Contributors
Author-email: hansbug@buaa.edu.cn
License: Apache License, Version 2.0
Keywords: Tree-structured Value Management
Classifier: Development Status :: 5 - Production/Stable
Classifier: Intended Audience :: Developers
Classifier: License :: OSI Approved :: Apache Software License
Classifier: Programming Language :: Python
Classifier: Programming Language :: Python :: 3
Classifier: Programming Language :: Python :: 3.8
Classifier: Programming Language :: Python :: 3.9
Classifier: Programming Language :: Python :: 3.10
Classifier: Programming Language :: Python :: 3.11
Classifier: Programming Language :: Python :: 3.12
Requires-Python: >=3.8
License-File: LICENSE
Requires-Dist: enum_tools
Requires-Dist: graphviz>=0.17
Requires-Dist: dill>=0.3.4
Requires-Dist: click>=7.1.0
Requires-Dist: hbutils>=0.9.1
Provides-Extra: benchmark
Requires-Dist: pytest-benchmark~=3.4.0; extra == "benchmark"
Requires-Dist: dm-tree>=0.1.6; extra == "benchmark"
Requires-Dist: tianshou>=0.4.5; extra == "benchmark"
Requires-Dist: jax[cpu]>=0.2.17; extra == "benchmark"
Requires-Dist: pandas; extra == "benchmark"
Requires-Dist: click>=7.0.0; extra == "benchmark"
Requires-Dist: numpy<2; extra == "benchmark"
Provides-Extra: test
Requires-Dist: coverage>=5; extra == "test"
Requires-Dist: mock>=4.0.3; extra == "test"
Requires-Dist: flake8~=3.5; extra == "test"
Requires-Dist: pytest~=6.2.5; extra == "test"
Requires-Dist: pytest-cov~=3.0.0; extra == "test"
Requires-Dist: pytest-mock~=3.6.1; extra == "test"
Requires-Dist: pytest-xdist>=1.34.0; extra == "test"
Requires-Dist: pytest-rerunfailures~=10.2; extra == "test"
Requires-Dist: pytest-timeout~=2.0.2; extra == "test"
Requires-Dist: pytest-benchmark~=3.4.0; extra == "test"
Requires-Dist: testtools>=2; extra == "test"
Requires-Dist: hbutils>=0.6.13; extra == "test"
Requires-Dist: setuptools; extra == "test"
Requires-Dist: numpy<2,>=1.10; python_version <= "3.9" and extra == "test"
Requires-Dist: numpy>=1.10; python_version > "3.9" and extra == "test"
Requires-Dist: easydict<2,>=1.7; extra == "test"
Provides-Extra: doc
Requires-Dist: Jinja2~=3.0.0; extra == "doc"
Requires-Dist: sphinx~=3.2.0; extra == "doc"
Requires-Dist: sphinx_rtd_theme~=0.4.3; extra == "doc"
Requires-Dist: enum_tools~=0.9.0; extra == "doc"
Requires-Dist: sphinx-toolbox; extra == "doc"
Requires-Dist: plantumlcli>=0.0.4; extra == "doc"
Requires-Dist: packaging; extra == "doc"
Requires-Dist: sphinx-multiversion~=0.2.4; extra == "doc"
Requires-Dist: where~=1.0.2; extra == "doc"
Requires-Dist: numpy<2,>=1.19; extra == "doc"
Requires-Dist: easydict<2,>=1.7; extra == "doc"
Requires-Dist: scikit-learn>=0.24.2; extra == "doc"
Requires-Dist: potc-treevalue>=0.0.1; extra == "doc"
Requires-Dist: nbsphinx>=0.8.8; extra == "doc"
Requires-Dist: ipython>=7.16.3; extra == "doc"
Requires-Dist: psutil>=5.8.0; extra == "doc"
Requires-Dist: ipykernel>=6.15; extra == "doc"
Requires-Dist: py-cpuinfo>=8.0.0; extra == "doc"
Provides-Extra: build
Requires-Dist: cython>=3; extra == "build"
Requires-Dist: build>=0.7.0; extra == "build"
Requires-Dist: auditwheel>=4; extra == "build"
Provides-Extra: potc
Requires-Dist: potc-treevalue>=0.0.1; extra == "potc"
